larch/__init__.py
larch/_version.py
larch/cli.py
larch/request_models.py
larch/server.py
larch/context_creator/__init__.py
larch/context_creator/all_data.py
larch/context_creator/common.py
larch/context_creator/dummy.py
larch/context_creator/entrypoint.py
larch/context_creator/file_filter.py
larch/context_creator/file_names.py
larch/context_creator/model.py
larch/context_creator/random_file.py
larch/entrypoint_extractor/__init__.py
larch/entrypoint_extractor/entrypoint_extractor.py
larch/entrypoint_extractor/features/__init__.py
larch/entrypoint_extractor/features/common.py
larch/entrypoint_extractor/features/content.py
larch/entrypoint_extractor/features/filename.py
larch/entrypoint_extractor/features/imports.py
larch/entrypoint_extractor/features/inheritance.py
larch/entrypoint_extractor/features/oracle.py
larch/evaluation/__init__.py
larch/evaluation/bleu.py
larch/evaluation/evaluation.py
larch/evaluation/postprocess.py
larch/evaluation/rouge.py
larch/generator/__init__.py
larch/generator/base.py
larch/generator/encoder_decoder.py
larch/generator/gpt2.py
larch/generator/gpt3.py
larch/postprocessor/__init__.py
larch/postprocessor/postprocessor.py
larch/utils/__init__.py
larch/utils/download.py
larch/utils/enum.py
larch/utils/language_detection.py
larch/utils/markdown.py
larch/utils/regex.py
larch/utils/spinner_utils.py
larch/utils/tqdm.py
larch_readme-0.0.10.dist-info/LICENSE
larch_readme-0.0.10.dist-info/METADATA
larch_readme-0.0.10.dist-info/WHEEL
larch_readme-0.0.10.dist-info/entry_points.txt
larch_readme-0.0.10.dist-info/top_level.txt
larch_readme-0.0.10.dist-info/RECORD
