Metadata-Version: 2.1
Name: larch-readme
Version: 0.0.10
Summary: Automatic readme generation using language models
Home-page: https://github.com/hitachi-nlp/larch
Author: Yuta Koreeda
Author-email: yuta.koreeda.pb@hitachi.com
Maintainer: Yuta Koreeda
Maintainer-email: yuta.koreeda.pb@hitachi.com
Classifier: Environment :: Console
Classifier: Development Status :: 4 - Beta
Classifier: Intended Audience :: Developers
Classifier: Intended Audience :: Education
Classifier: Intended Audience :: Science/Research
Classifier: Operating System :: OS Independent
Classifier: Programming Language :: Python :: 3.8
Classifier: Topic :: Scientific/Engineering :: Artificial Intelligence
Classifier: Topic :: Scientific/Engineering :: Information Analysis
License-File: LICENSE
Requires-Dist: click (==8.1.3)
Requires-Dist: torch (==1.13.0)
Requires-Dist: transformers (==4.23.0)
Requires-Dist: requests (>=2.27.1)
Requires-Dist: fastapi[all] (==0.96.0)
Requires-Dist: wheel
Requires-Dist: yaspin (>=2.1.0)
Requires-Dist: tqdm (>=4.64.0)
Requires-Dist: networkx (==2.8.8)
Requires-Dist: snorkel (==0.9.9)
Requires-Dist: pandas
Requires-Dist: numpy
Requires-Dist: joblib
Requires-Dist: xgboost (==1.7.1)
Requires-Dist: pydantic (>=1.10.9)
